[
    {
        "command": "Block",
        "list": [
            {
                "command_id": 2,
                "command": "Bg",
                "command_option": "On",
                "command_time": 0,
                "resorce_id": 100142,
                "bg_option": {
                    "position_x": null,
                    "position_y": null,
                    "scale": null
                }
            },
            {
                "command_id": 3,
                "command": "Transition",
                "command_option": "In",
                "command_time": 2,
                "resorce_id": 0
            }
        ]
    },
    {
        "command_id": 5,
        "command": "Title",
        "command_option": null,
        "command_time": null,
        "resorce_id": null,
        "title_option": {
            "main_text": "戦闘もイチャイチャです！",
            "sub_text": "アルナイル"
        }
    },
    {
        "command_id": 6,
        "command": "Wait",
        "command_option": null,
        "command_time": 0.1,
        "resorce_id": null
    },
    {
        "command_id": 7,
        "command": "Bgm",
        "command_option": "On",
        "command_time": 0,
        "resorce_id": 100101
    },
    {
        "command_id": 10,
        "command": "Character",
        "command_option": "On",
        "command_time": 0.3,
        "resorce_id": 200130,
        "character_option": {
            "body_variation": 1,
            "face_variation": 14,
            "position_x": 0,
            "position_y": 0,
            "scale": null
        }
    },
    {
        "command_id": 11,
        "command": "Wait",
        "command_option": null,
        "command_time": 0.3,
        "resorce_id": null
    },
    {
        "command": "Block",
        "list": [
            {
                "command_id": 13,
                "command": "Character",
                "command_option": "On",
                "command_time": null,
                "resorce_id": 200130,
                "character_option": {
                    "body_variation": 1,
                    "face_variation": 14,
                    "position_x": 0,
                    "position_y": 0,
                    "scale": null
                }
            },
            {
                "command_id": 14,
                "command": "Text",
                "command_option": null,
                "command_time": null,
                "resorce_id": 200130,
                "text_option": {
                    "character_name": "アルナイル",
                    "character_text": "マスター、わたし考えたんですけど……",
                    "voice": "200100_adv_001_001_001",
                    "voice_option": null
                }
            }
        ]
    },
    {
        "command": "Block",
        "list": [
            {
                "command_id": 17,
                "command": "Text",
                "command_option": "Off",
                "command_time": 0.1,
                "resorce_id": null,
                "text_option": {
                    "character_name": null,
                    "character_text": null,
                    "voice": null,
                    "voice_option": null
                }
            },
            {
                "command_id": 18,
                "command": "Character",
                "command_option": "Move",
                "command_time": 0.2,
                "resorce_id": 200130,
                "character_option": {
                    "body_variation": 1,
                    "face_variation": 12,
                    "position_x": 0,
                    "position_y": -5,
                    "scale": null
                }
            }
        ]
    },
    {
        "command_id": 20,
        "command": "Character",
        "command_option": "Move",
        "command_time": 0.15,
        "resorce_id": 200130,
        "character_option": {
            "body_variation": 1,
            "face_variation": 12,
            "position_x": 0,
            "position_y": -7,
            "scale": null
        }
    },
    {
        "command_id": 21,
        "command": "Character",
        "command_option": "Move",
        "command_time": 0.15,
        "resorce_id": 200130,
        "character_option": {
            "body_variation": 1,
            "face_variation": 12,
            "position_x": 0,
            "position_y": -3,
            "scale": null
        }
    },
    {
        "command": "Block",
        "list": [
            {
                "command_id": 23,
                "command": "Character",
                "command_option": "Move",
                "command_time": 0.05,
                "resorce_id": 200130,
                "character_option": {
                    "body_variation": 1,
                    "face_variation": 12,
                    "position_x": 0,
                    "position_y": 0,
                    "scale": null
                }
            },
            {
                "command_id": 24,
                "command": "Text",
                "command_option": null,
                "command_time": null,
                "resorce_id": 200130,
                "text_option": {
                    "character_name": "アルナイル",
                    "character_text": "この衣装で戦闘データを収集するのに、\n普段みたいに、他の皆さんと一緒に戦うんじゃなくて……",
                    "voice": "200100_adv_000_001_030",
                    "voice_option": null
                }
            }
        ]
    },
    {
        "command": "Block",
        "list": [
            {
                "command_id": 27,
                "command": "Character",
                "command_option": "On",
                "command_time": null,
                "resorce_id": 200130,
                "character_option": {
                    "body_variation": 1,
                    "face_variation": 3,
                    "position_x": 0,
                    "position_y": 0,
                    "scale": null
                }
            },
            {
                "command_id": 28,
                "command": "Text",
                "command_option": null,
                "command_time": null,
                "resorce_id": 200130,
                "text_option": {
                    "character_name": "アルナイル",
                    "character_text": "わたしひとりの方が、データを取りやすいんじゃないかなって、\n思ったんですけど",
                    "voice": "200100_adv_002_001_004",
                    "voice_option": null
                }
            }
        ]
    },
    {
        "command": "Block",
        "list": [
            {
                "command_id": 31,
                "command": "Text",
                "command_option": "Off",
                "command_time": 0.1,
                "resorce_id": null,
                "text_option": {
                    "character_name": null,
                    "character_text": null,
                    "voice": null,
                    "voice_option": null
                }
            },
            {
                "command_id": 32,
                "command": "Character",
                "command_option": "Move",
                "command_time": 0.2,
                "resorce_id": 200130,
                "character_option": {
                    "body_variation": 1,
                    "face_variation": 13,
                    "position_x": 2,
                    "position_y": 0,
                    "scale": null
                }
            }
        ]
    },
    {
        "command_id": 34,
        "command": "Character",
        "command_option": "Move",
        "command_time": 0.2,
        "resorce_id": 200130,
        "character_option": {
            "body_variation": 1,
            "face_variation": 13,
            "position_x": -2,
            "position_y": 0,
            "scale": null
        }
    },
    {
        "command": "Block",
        "list": [
            {
                "command_id": 36,
                "command": "Character",
                "command_option": "Move",
                "command_time": 0.2,
                "resorce_id": 200130,
                "character_option": {
                    "body_variation": 1,
                    "face_variation": 13,
                    "position_x": 0,
                    "position_y": 0,
                    "scale": null
                }
            },
            {
                "command_id": 37,
                "command": "Text",
                "command_option": null,
                "command_time": null,
                "resorce_id": 200130,
                "text_option": {
                    "character_name": "アルナイル",
                    "character_text": "他の皆さんと一緒だと、皆さんのお力も加わってしまって、この\n衣装の性能をはかるデータとしては、わかりにくいのかな、って",
                    "voice": "200110_adv_001_001_001",
                    "voice_option": null
                }
            }
        ]
    },
    {
        "command": "Block",
        "list": [
            {
                "command_id": 40,
                "command": "Character",
                "command_option": "On",
                "command_time": null,
                "resorce_id": 200130,
                "character_option": {
                    "body_variation": 1,
                    "face_variation": 14,
                    "position_x": 0,
                    "position_y": 0,
                    "scale": null
                }
            },
            {
                "command_id": 41,
                "command": "Text",
                "command_option": null,
                "command_time": null,
                "resorce_id": 200130,
                "text_option": {
                    "character_name": "アルナイル",
                    "character_text": "そうかも知れない？　マスターもそう思いますか？",
                    "voice": "200100_adv_003_019_001",
                    "voice_option": null
                }
            }
        ]
    },
    {
        "command": "Block",
        "list": [
            {
                "command_id": 44,
                "command": "Text",
                "command_option": "Off",
                "command_time": 0.1,
                "resorce_id": null,
                "text_option": {
                    "character_name": null,
                    "character_text": null,
                    "voice": null,
                    "voice_option": null
                }
            },
            {
                "command_id": 45,
                "command": "Character",
                "command_option": "Move",
                "command_time": 0.1,
                "resorce_id": 200130,
                "character_option": {
                    "body_variation": 1,
                    "face_variation": 6,
                    "position_x": 0,
                    "position_y": -5,
                    "scale": null
                }
            }
        ]
    },
    {
        "command_id": 47,
        "command": "Character",
        "command_option": "Move",
        "command_time": 0.05,
        "resorce_id": 200130,
        "character_option": {
            "body_variation": 1,
            "face_variation": 6,
            "position_x": 0,
            "position_y": -7,
            "scale": null
        }
    },
    {
        "command_id": 48,
        "command": "Character",
        "command_option": "Move",
        "command_time": 0.05,
        "resorce_id": 200130,
        "character_option": {
            "body_variation": 1,
            "face_variation": 6,
            "position_x": 0,
            "position_y": -3,
            "scale": null
        }
    },
    {
        "command": "Block",
        "list": [
            {
                "command_id": 50,
                "command": "Character",
                "command_option": "Move",
                "command_time": 0.01,
                "resorce_id": 200130,
                "character_option": {
                    "body_variation": 1,
                    "face_variation": 6,
                    "position_x": 0,
                    "position_y": 0,
                    "scale": null
                }
            },
            {
                "command_id": 51,
                "command": "Text",
                "command_option": null,
                "command_time": null,
                "resorce_id": 200130,
                "text_option": {
                    "character_name": "アルナイル",
                    "character_text": "じゃあ、わたしの考えはそんなに見当違いじゃないんですね、\n良かった♪",
                    "voice": "200100_adv_003_017_001",
                    "voice_option": null
                }
            }
        ]
    },
    {
        "command": "Block",
        "list": [
            {
                "command_id": 54,
                "command": "Text",
                "command_option": "Off",
                "command_time": 0.1,
                "resorce_id": null,
                "text_option": {
                    "character_name": null,
                    "character_text": null,
                    "voice": null,
                    "voice_option": null
                }
            },
            {
                "command_id": 55,
                "command": "Character",
                "command_option": "Move",
                "command_time": 0.2,
                "resorce_id": 200130,
                "character_option": {
                    "body_variation": 1,
                    "face_variation": 1,
                    "position_x": 2,
                    "position_y": 0,
                    "scale": null
                }
            }
        ]
    },
    {
        "command_id": 57,
        "command": "Character",
        "command_option": "Move",
        "command_time": 0.2,
        "resorce_id": 200130,
        "character_option": {
            "body_variation": 1,
            "face_variation": 1,
            "position_x": -2,
            "position_y": 0,
            "scale": null
        }
    },
    {
        "command": "Block",
        "list": [
            {
                "command_id": 59,
                "command": "Character",
                "command_option": "Move",
                "command_time": 0.2,
                "resorce_id": 200130,
                "character_option": {
                    "body_variation": 1,
                    "face_variation": 1,
                    "position_x": 0,
                    "position_y": 0,
                    "scale": null
                }
            },
            {
                "command_id": 60,
                "command": "Text",
                "command_option": null,
                "command_time": null,
                "resorce_id": 200130,
                "text_option": {
                    "character_name": "アルナイル",
                    "character_text": "そう言われると確かに、\nその新しい衣装の性能を純粋に試してみたい気もする、ですか？",
                    "voice": "200110_adv_003_004_001",
                    "voice_option": null
                }
            }
        ]
    },
    {
        "command": "Block",
        "list": [
            {
                "command_id": 63,
                "command": "Text",
                "command_option": "Off",
                "command_time": 0.15,
                "resorce_id": null,
                "text_option": {
                    "character_name": null,
                    "character_text": null,
                    "voice": null,
                    "voice_option": null
                }
            },
            {
                "command_id": 64,
                "command": "Character",
                "command_option": "Move",
                "command_time": 0.15,
                "resorce_id": 200130,
                "character_option": {
                    "body_variation": 1,
                    "face_variation": 14,
                    "position_x": 0,
                    "position_y": -5,
                    "scale": null
                }
            }
        ]
    },
    {
        "command_id": 66,
        "command": "Character",
        "command_option": "Move",
        "command_time": 0.1,
        "resorce_id": 200130,
        "character_option": {
            "body_variation": 1,
            "face_variation": 14,
            "position_x": 0,
            "position_y": -7,
            "scale": null
        }
    },
    {
        "command_id": 67,
        "command": "Character",
        "command_option": "Move",
        "command_time": 0.1,
        "resorce_id": 200130,
        "character_option": {
            "body_variation": 1,
            "face_variation": 14,
            "position_x": 0,
            "position_y": -3,
            "scale": null
        }
    },
    {
        "command": "Block",
        "list": [
            {
                "command_id": 69,
                "command": "Character",
                "command_option": "Move",
                "command_time": 0.02,
                "resorce_id": 200130,
                "character_option": {
                    "body_variation": 1,
                    "face_variation": 14,
                    "position_x": 0,
                    "position_y": 0,
                    "scale": null
                }
            },
            {
                "command_id": 70,
                "command": "Text",
                "command_option": null,
                "command_time": null,
                "resorce_id": 200130,
                "text_option": {
                    "character_name": "アルナイル",
                    "character_text": "あ、それでしたらマスター、戦闘データをとるのに、\n丁度良いサーバがあるので、そこへ行きませんかっ",
                    "voice": "200110_adv_003_007_001",
                    "voice_option": null
                }
            }
        ]
    },
    {
        "command_id": 75,
        "command": "Transition",
        "command_option": "Out",
        "command_time": 0.5,
        "resorce_id": null
    },
    {
        "command": "Block",
        "list": [
            {
                "command_id": 77,
                "command": "Bg",
                "command_option": "On",
                "command_time": 0.1,
                "resorce_id": 100156,
                "bg_option": {
                    "position_x": null,
                    "position_y": null,
                    "scale": null
                }
            },
            {
                "command_id": 78,
                "command": "Character",
                "command_option": "OffAll",
                "command_time": 0.1,
                "resorce_id": null,
                "character_option": {
                    "body_variation": null,
                    "face_variation": null,
                    "position_x": null,
                    "position_y": null,
                    "scale": null
                }
            },
            {
                "command_id": 79,
                "command": "Text",
                "command_option": "Off",
                "command_time": 0.1,
                "resorce_id": null,
                "text_option": {
                    "character_name": null,
                    "character_text": null,
                    "voice": null,
                    "voice_option": null
                }
            }
        ]
    },
    {
        "command_id": 81,
        "command": "Wait",
        "command_option": null,
        "command_time": 1,
        "resorce_id": null
    },
    {
        "command_id": 82,
        "command": "Transition",
        "command_option": "In",
        "command_time": 0.5,
        "resorce_id": null
    },
    {
        "command_id": 83,
        "command": "Wait",
        "command_option": null,
        "command_time": 0.7,
        "resorce_id": null
    },
    {
        "command_id": 84,
        "command": "Character",
        "command_option": "On",
        "command_time": 0.3,
        "resorce_id": 200130,
        "character_option": {
            "body_variation": 1,
            "face_variation": 14,
            "position_x": 0,
            "position_y": 0,
            "scale": null
        }
    },
    {
        "command_id": 85,
        "command": "Wait",
        "command_option": null,
        "command_time": 0.3,
        "resorce_id": null
    },
    {
        "command": "Block",
        "list": [
            {
                "command_id": 87,
                "command": "Character",
                "command_option": "On",
                "command_time": null,
                "resorce_id": 200130,
                "character_option": {
                    "body_variation": 1,
                    "face_variation": 14,
                    "position_x": 0,
                    "position_y": 0,
                    "scale": null
                }
            },
            {
                "command_id": 88,
                "command": "Text",
                "command_option": null,
                "command_time": null,
                "resorce_id": 200130,
                "text_option": {
                    "character_name": "アルナイル",
                    "character_text": "ここなら、わたしひとりでも安心安全なレベルの悪魔さんしか\n居ないですから、戦闘データを集めるにはピッタリだと思います！",
                    "voice": "200110_adv_002_001_001",
                    "voice_option": null
                }
            }
        ]
    },
    {
        "command": "Block",
        "list": [
            {
                "command_id": 91,
                "command": "Text",
                "command_option": "Off",
                "command_time": 0.1,
                "resorce_id": null,
                "text_option": {
                    "character_name": null,
                    "character_text": null,
                    "voice": null,
                    "voice_option": null
                }
            },
            {
                "command_id": 92,
                "command": "Character",
                "command_option": "Move",
                "command_time": 0.2,
                "resorce_id": 200130,
                "character_option": {
                    "body_variation": 1,
                    "face_variation": 12,
                    "position_x": 2,
                    "position_y": 0,
                    "scale": null
                }
            }
        ]
    },
    {
        "command_id": 94,
        "command": "Character",
        "command_option": "Move",
        "command_time": 0.2,
        "resorce_id": 200130,
        "character_option": {
            "body_variation": 1,
            "face_variation": 12,
            "position_x": -2,
            "position_y": 0,
            "scale": null
        }
    },
    {
        "command_id": 95,
        "command": "Character",
        "command_option": "Move",
        "command_time": 0.2,
        "resorce_id": 200130,
        "character_option": {
            "body_variation": 1,
            "face_variation": 12,
            "position_x": 0,
            "position_y": 0,
            "scale": null
        }
    },
    {
        "command_id": 96,
        "command": "Wait",
        "command_option": null,
        "command_time": 0.2,
        "resorce_id": null
    },
    {
        "command_id": 97,
        "command": "Character",
        "command_option": "Move",
        "command_time": 0.1,
        "resorce_id": 200130,
        "character_option": {
            "body_variation": 1,
            "face_variation": 2,
            "position_x": 0,
            "position_y": -5,
            "scale": null
        }
    },
    {
        "command_id": 98,
        "command": "Character",
        "command_option": "Move",
        "command_time": 0.05,
        "resorce_id": 200130,
        "character_option": {
            "body_variation": 1,
            "face_variation": 2,
            "position_x": 0,
            "position_y": -7,
            "scale": null
        }
    },
    {
        "command_id": 99,
        "command": "Character",
        "command_option": "Move",
        "command_time": 0.05,
        "resorce_id": 200130,
        "character_option": {
            "body_variation": 1,
            "face_variation": 2,
            "position_x": 0,
            "position_y": -3,
            "scale": null
        }
    },
    {
        "command": "Block",
        "list": [
            {
                "command_id": 101,
                "command": "Character",
                "command_option": "Move",
                "command_time": 0.01,
                "resorce_id": 200130,
                "character_option": {
                    "body_variation": 1,
                    "face_variation": 2,
                    "position_x": 0,
                    "position_y": 0,
                    "scale": null
                }
            },
            {
                "command_id": 102,
                "command": "Text",
                "command_option": null,
                "command_time": null,
                "resorce_id": 200130,
                "text_option": {
                    "character_name": "アルナイル",
                    "character_text": "では、ここの悪魔さんにはすこし申し訳ないですけど、\n張り切って戦闘しちゃいましょー！",
                    "voice": "200130_battle_000_attack3_001",
                    "voice_option": null
                }
            }
        ]
    },
    {
        "command": "Block",
        "list": [
            {
                "command_id": 105,
                "command": "Text",
                "command_option": "Off",
                "command_time": 0.1,
                "resorce_id": null,
                "text_option": {
                    "character_name": null,
                    "character_text": null,
                    "voice": null,
                    "voice_option": null
                }
            },
            {
                "command_id": 106,
                "command": "Character",
                "command_option": "Move",
                "command_time": 0.2,
                "resorce_id": 200130,
                "character_option": {
                    "body_variation": 1,
                    "face_variation": 6,
                    "position_x": 0,
                    "position_y": -5,
                    "scale": null
                }
            }
        ]
    },
    {
        "command_id": 108,
        "command": "Character",
        "command_option": "Move",
        "command_time": 0.15,
        "resorce_id": 200130,
        "character_option": {
            "body_variation": 1,
            "face_variation": 6,
            "position_x": 0,
            "position_y": -7,
            "scale": null
        }
    },
    {
        "command_id": 109,
        "command": "Character",
        "command_option": "Move",
        "command_time": 0.15,
        "resorce_id": 200130,
        "character_option": {
            "body_variation": 1,
            "face_variation": 6,
            "position_x": 0,
            "position_y": -3,
            "scale": null
        }
    },
    {
        "command": "Block",
        "list": [
            {
                "command_id": 111,
                "command": "Character",
                "command_option": "Move",
                "command_time": 0.05,
                "resorce_id": 200130,
                "character_option": {
                    "body_variation": 1,
                    "face_variation": 6,
                    "position_x": 0,
                    "position_y": 0,
                    "scale": null
                }
            },
            {
                "command_id": 112,
                "command": "Text",
                "command_option": null,
                "command_time": null,
                "resorce_id": 200130,
                "text_option": {
                    "character_name": "アルナイル",
                    "character_text": "この世界のために、マスターのために、わたし頑張っちゃいますね",
                    "voice": "200110_battle_000_act1_001",
                    "voice_option": null
                }
            }
        ]
    },
    {
        "command_id": 117,
        "command": "Transition",
        "command_option": "Out",
        "command_time": 0.5,
        "resorce_id": null
    },
    {
        "command": "Block",
        "list": [
            {
                "command_id": 119,
                "command": "Character",
                "command_option": "OffAll",
                "command_time": 0.1,
                "resorce_id": null,
                "character_option": {
                    "body_variation": null,
                    "face_variation": null,
                    "position_x": null,
                    "position_y": null,
                    "scale": null
                }
            },
            {
                "command_id": 120,
                "command": "Text",
                "command_option": "Off",
                "command_time": 0.1,
                "resorce_id": null,
                "text_option": {
                    "character_name": null,
                    "character_text": null,
                    "voice": null,
                    "voice_option": null
                }
            }
        ]
    },
    {
        "command_id": 122,
        "command": "Wait",
        "command_option": null,
        "command_time": 1,
        "resorce_id": null
    },
    {
        "command_id": 123,
        "command": "Transition",
        "command_option": "In",
        "command_time": 0.5,
        "resorce_id": null
    },
    {
        "command_id": 124,
        "command": "Wait",
        "command_option": null,
        "command_time": 0.6,
        "resorce_id": null
    },
    {
        "command": "Block",
        "list": [
            {
                "command_id": 126,
                "command": "Character",
                "command_option": "On",
                "command_time": 0.2,
                "resorce_id": 200130,
                "character_option": {
                    "body_variation": 1,
                    "face_variation": 12,
                    "position_x": 0,
                    "position_y": 0,
                    "scale": null
                }
            },
            {
                "command_id": 127,
                "command": "Character",
                "command_option": "Move",
                "command_time": 0.2,
                "resorce_id": 200130,
                "character_option": {
                    "body_variation": 1,
                    "face_variation": 12,
                    "position_x": 0,
                    "position_y": -5,
                    "scale": null
                }
            }
        ]
    },
    {
        "command_id": 129,
        "command": "Character",
        "command_option": "Move",
        "command_time": 0.15,
        "resorce_id": 200130,
        "character_option": {
            "body_variation": 1,
            "face_variation": 12,
            "position_x": 0,
            "position_y": -7,
            "scale": null
        }
    },
    {
        "command_id": 130,
        "command": "Character",
        "command_option": "Move",
        "command_time": 0.15,
        "resorce_id": 200130,
        "character_option": {
            "body_variation": 1,
            "face_variation": 12,
            "position_x": 0,
            "position_y": -3,
            "scale": null
        }
    },
    {
        "command": "Block",
        "list": [
            {
                "command_id": 132,
                "command": "Character",
                "command_option": "Move",
                "command_time": 0.05,
                "resorce_id": 200130,
                "character_option": {
                    "body_variation": 1,
                    "face_variation": 12,
                    "position_x": 0,
                    "position_y": 0,
                    "scale": null
                }
            },
            {
                "command_id": 133,
                "command": "Text",
                "command_option": null,
                "command_time": null,
                "resorce_id": 200130,
                "text_option": {
                    "character_name": "アルナイル",
                    "character_text": "マスター、やっぱりこの新衣装、\n今までの衣装よりも力が溢れてきますっ",
                    "voice": "200130_battle_000_end1_001",
                    "voice_option": null
                }
            }
        ]
    },
    {
        "command": "Block",
        "list": [
            {
                "command_id": 136,
                "command": "Character",
                "command_option": "On",
                "command_time": null,
                "resorce_id": 200130,
                "character_option": {
                    "body_variation": 1,
                    "face_variation": 3,
                    "position_x": 0,
                    "position_y": 0,
                    "scale": null
                }
            },
            {
                "command_id": 137,
                "command": "Text",
                "command_option": null,
                "command_time": null,
                "resorce_id": 200130,
                "text_option": {
                    "character_name": "アルナイル",
                    "character_text": "それに、マスターが応援してくれると、すごく力が湧いてきます",
                    "voice": "200120_adv_003_010_001",
                    "voice_option": null
                }
            }
        ]
    },
    {
        "command": "Block",
        "list": [
            {
                "command_id": 140,
                "command": "Text",
                "command_option": "Off",
                "command_time": 0.1,
                "resorce_id": null,
                "text_option": {
                    "character_name": null,
                    "character_text": null,
                    "voice": null,
                    "voice_option": null
                }
            },
            {
                "command_id": 141,
                "command": "Character",
                "command_option": "Move",
                "command_time": 0.2,
                "resorce_id": 200130,
                "character_option": {
                    "body_variation": 1,
                    "face_variation": 14,
                    "position_x": 2,
                    "position_y": 0,
                    "scale": null
                }
            }
        ]
    },
    {
        "command_id": 143,
        "command": "Character",
        "command_option": "Move",
        "command_time": 0.2,
        "resorce_id": 200130,
        "character_option": {
            "body_variation": 1,
            "face_variation": 14,
            "position_x": -2,
            "position_y": 0,
            "scale": null
        }
    },
    {
        "command": "Block",
        "list": [
            {
                "command_id": 145,
                "command": "Character",
                "command_option": "Move",
                "command_time": 0.2,
                "resorce_id": 200130,
                "character_option": {
                    "body_variation": 1,
                    "face_variation": 14,
                    "position_x": 0,
                    "position_y": 0,
                    "scale": null
                }
            },
            {
                "command_id": 146,
                "command": "Text",
                "command_option": null,
                "command_time": null,
                "resorce_id": 200130,
                "text_option": {
                    "character_name": "アルナイル",
                    "character_text": "えっ？　マスターが時々、『いいぞーアルー！』とか、\n『頑張れ―！』とか、声をかけて下さるじゃないですか",
                    "voice": "200100_adv_002_004_001",
                    "voice_option": null
                }
            }
        ]
    },
    {
        "command": "Block",
        "list": [
            {
                "command_id": 149,
                "command": "Text",
                "command_option": "Off",
                "command_time": 0.1,
                "resorce_id": null,
                "text_option": {
                    "character_name": null,
                    "character_text": null,
                    "voice": null,
                    "voice_option": null
                }
            },
            {
                "command_id": 150,
                "command": "Character",
                "command_option": "Move",
                "command_time": 0.2,
                "resorce_id": 200130,
                "character_option": {
                    "body_variation": 1,
                    "face_variation": 2,
                    "position_x": 0,
                    "position_y": -5,
                    "scale": null
                }
            }
        ]
    },
    {
        "command_id": 152,
        "command": "Character",
        "command_option": "Move",
        "command_time": 0.15,
        "resorce_id": 200130,
        "character_option": {
            "body_variation": 1,
            "face_variation": 2,
            "position_x": 0,
            "position_y": -7,
            "scale": null
        }
    },
    {
        "command_id": 153,
        "command": "Character",
        "command_option": "Move",
        "command_time": 0.15,
        "resorce_id": 200130,
        "character_option": {
            "body_variation": 1,
            "face_variation": 2,
            "position_x": 0,
            "position_y": -3,
            "scale": null
        }
    },
    {
        "command": "Block",
        "list": [
            {
                "command_id": 155,
                "command": "Character",
                "command_option": "Move",
                "command_time": 0.05,
                "resorce_id": 200130,
                "character_option": {
                    "body_variation": 1,
                    "face_variation": 2,
                    "position_x": 0,
                    "position_y": 0,
                    "scale": null
                }
            },
            {
                "command_id": 156,
                "command": "Text",
                "command_option": null,
                "command_time": null,
                "resorce_id": 200130,
                "text_option": {
                    "character_name": "アルナイル",
                    "character_text": "そういう時に、ググッ！　と、なんだか格段に、力が溢れてくる\nというか……はい、ダメージ数値にも反映されてると思います！",
                    "voice": "200100_adv_002_001_008",
                    "voice_option": null
                }
            }
        ]
    },
    {
        "command_id": 158,
        "command": "Text",
        "command_option": "Off",
        "command_time": 0.3,
        "resorce_id": null,
        "text_option": {
            "character_name": null,
            "character_text": null,
            "voice": null,
            "voice_option": null
        }
    },
    {
        "command_id": 159,
        "command": "Wait",
        "command_option": null,
        "command_time": 0.3,
        "resorce_id": null
    },
    {
        "command": "Block",
        "list": [
            {
                "command_id": 161,
                "command": "Character",
                "command_option": "On",
                "command_time": null,
                "resorce_id": 200130,
                "character_option": {
                    "body_variation": 1,
                    "face_variation": 9,
                    "position_x": 0,
                    "position_y": 0,
                    "scale": null
                }
            },
            {
                "command_id": 162,
                "command": "Text",
                "command_option": null,
                "command_time": null,
                "resorce_id": 200130,
                "text_option": {
                    "character_name": "アルナイル",
                    "character_text": "……っ！？",
                    "voice": "200100_adv_003_016_001",
                    "voice_option": null
                }
            }
        ]
    },
    {
        "command": "Block",
        "list": [
            {
                "command_id": 165,
                "command": "Text",
                "command_option": "Off",
                "command_time": 0.1,
                "resorce_id": null,
                "text_option": {
                    "character_name": null,
                    "character_text": null,
                    "voice": null,
                    "voice_option": null
                }
            },
            {
                "command_id": 166,
                "command": "Character",
                "command_option": "Move",
                "command_time": 0.2,
                "resorce_id": 200130,
                "character_option": {
                    "body_variation": 1,
                    "face_variation": 9,
                    "position_x": 2,
                    "position_y": 0,
                    "scale": null
                }
            }
        ]
    },
    {
        "command_id": 168,
        "command": "Character",
        "command_option": "Move",
        "command_time": 0.2,
        "resorce_id": 200130,
        "character_option": {
            "body_variation": 1,
            "face_variation": 9,
            "position_x": -2,
            "position_y": 0,
            "scale": null
        }
    },
    {
        "command": "Block",
        "list": [
            {
                "command_id": 170,
                "command": "Character",
                "command_option": "Move",
                "command_time": 0.2,
                "resorce_id": 200130,
                "character_option": {
                    "body_variation": 1,
                    "face_variation": 9,
                    "position_x": 0,
                    "position_y": 0,
                    "scale": null
                }
            },
            {
                "command_id": 171,
                "command": "Text",
                "command_option": null,
                "command_time": null,
                "resorce_id": 200130,
                "text_option": {
                    "character_name": "アルナイル",
                    "character_text": "（い、今っ！　マスターが……っ）",
                    "voice": "200110_adv_003_012_001",
                    "voice_option": null
                }
            }
        ]
    },
    {
        "command": "Block",
        "list": [
            {
                "command_id": 174,
                "command": "Character",
                "command_option": "On",
                "command_time": null,
                "resorce_id": 200130,
                "character_option": {
                    "body_variation": 1,
                    "face_variation": 9,
                    "position_x": 0,
                    "position_y": 0,
                    "scale": null
                }
            },
            {
                "command_id": 175,
                "command": "Text",
                "command_option": null,
                "command_time": null,
                "resorce_id": 200130,
                "text_option": {
                    "character_name": "アルナイル",
                    "character_text": "（『じゃあキスしたら、もっと力が湧く？』って言ったのは……）",
                    "voice": "200120_adv_003_003_001",
                    "voice_option": null
                }
            }
        ]
    },
    {
        "command": "Block",
        "list": [
            {
                "command_id": 178,
                "command": "Text",
                "command_option": "Off",
                "command_time": 0.15,
                "resorce_id": null,
                "text_option": {
                    "character_name": null,
                    "character_text": null,
                    "voice": null,
                    "voice_option": null
                }
            },
            {
                "command_id": 179,
                "command": "Character",
                "command_option": "Move",
                "command_time": 0.15,
                "resorce_id": 200130,
                "character_option": {
                    "body_variation": 1,
                    "face_variation": 9,
                    "position_x": 0,
                    "position_y": -5,
                    "scale": null
                }
            }
        ]
    },
    {
        "command_id": 181,
        "command": "Character",
        "command_option": "Move",
        "command_time": 0.1,
        "resorce_id": 200130,
        "character_option": {
            "body_variation": 1,
            "face_variation": 9,
            "position_x": 0,
            "position_y": -7,
            "scale": null
        }
    },
    {
        "command_id": 182,
        "command": "Character",
        "command_option": "Move",
        "command_time": 0.1,
        "resorce_id": 200130,
        "character_option": {
            "body_variation": 1,
            "face_variation": 9,
            "position_x": 0,
            "position_y": -3,
            "scale": null
        }
    },
    {
        "command": "Block",
        "list": [
            {
                "command_id": 184,
                "command": "Character",
                "command_option": "Move",
                "command_time": 0.02,
                "resorce_id": 200130,
                "character_option": {
                    "body_variation": 1,
                    "face_variation": 9,
                    "position_x": 0,
                    "position_y": 0,
                    "scale": null
                }
            },
            {
                "command_id": 185,
                "command": "Text",
                "command_option": null,
                "command_time": null,
                "resorce_id": 200130,
                "text_option": {
                    "character_name": "アルナイル",
                    "character_text": "（わ、わたしの聞き間違いじゃない……ですよねっ……！？）",
                    "voice": "200120_adv_003_007_001",
                    "voice_option": null
                }
            }
        ]
    },
    {
        "command": "Block",
        "list": [
            {
                "command_id": 188,
                "command": "Text",
                "command_option": "Off",
                "command_time": 0.1,
                "resorce_id": null,
                "text_option": {
                    "character_name": null,
                    "character_text": null,
                    "voice": null,
                    "voice_option": null
                }
            },
            {
                "command_id": 189,
                "command": "Character",
                "command_option": "Move",
                "command_time": 0.2,
                "resorce_id": 200130,
                "character_option": {
                    "body_variation": 1,
                    "face_variation": 11,
                    "position_x": 2,
                    "position_y": 0,
                    "scale": null
                }
            }
        ]
    },
    {
        "command_id": 191,
        "command": "Character",
        "command_option": "Move",
        "command_time": 0.2,
        "resorce_id": 200130,
        "character_option": {
            "body_variation": 1,
            "face_variation": 11,
            "position_x": -2,
            "position_y": 0,
            "scale": null
        }
    },
    {
        "command": "Block",
        "list": [
            {
                "command_id": 193,
                "command": "Character",
                "command_option": "Move",
                "command_time": 0.2,
                "resorce_id": 200130,
                "character_option": {
                    "body_variation": 1,
                    "face_variation": 11,
                    "position_x": 0,
                    "position_y": 0,
                    "scale": null
                }
            },
            {
                "command_id": 194,
                "command": "Text",
                "command_option": null,
                "command_time": null,
                "resorce_id": 200130,
                "text_option": {
                    "character_name": "アルナイル",
                    "character_text": "マ、マスター……、あのぅ……",
                    "voice": "200100_adv_000_001_003",
                    "voice_option": null
                }
            }
        ]
    },
    {
        "command": "Block",
        "list": [
            {
                "command_id": 197,
                "command": "Text",
                "command_option": "Off",
                "command_time": 0.1,
                "resorce_id": null,
                "text_option": {
                    "character_name": null,
                    "character_text": null,
                    "voice": null,
                    "voice_option": null
                }
            },
            {
                "command_id": 198,
                "command": "Character",
                "command_option": "Move",
                "command_time": 0.2,
                "resorce_id": 200130,
                "character_option": {
                    "body_variation": 1,
                    "face_variation": 5,
                    "position_x": 0,
                    "position_y": -5,
                    "scale": null
                }
            }
        ]
    },
    {
        "command_id": 200,
        "command": "Character",
        "command_option": "Move",
        "command_time": 0.15,
        "resorce_id": 200130,
        "character_option": {
            "body_variation": 1,
            "face_variation": 5,
            "position_x": 0,
            "position_y": -7,
            "scale": null
        }
    },
    {
        "command_id": 201,
        "command": "Character",
        "command_option": "Move",
        "command_time": 0.15,
        "resorce_id": 200130,
        "character_option": {
            "body_variation": 1,
            "face_variation": 5,
            "position_x": 0,
            "position_y": -3,
            "scale": null
        }
    },
    {
        "command": "Block",
        "list": [
            {
                "command_id": 203,
                "command": "Character",
                "command_option": "Move",
                "command_time": 0.05,
                "resorce_id": 200130,
                "character_option": {
                    "body_variation": 1,
                    "face_variation": 5,
                    "position_x": 0,
                    "position_y": 0,
                    "scale": null
                }
            },
            {
                "command_id": 204,
                "command": "Text",
                "command_option": null,
                "command_time": null,
                "resorce_id": 200130,
                "text_option": {
                    "character_name": "アルナイル",
                    "character_text": "えっと、その……",
                    "voice": "200110_adv_001_002_001",
                    "voice_option": null
                }
            }
        ]
    },
    {
        "command": "Block",
        "list": [
            {
                "command_id": 208,
                "command": "Text",
                "command_option": "Off",
                "command_time": 0.1,
                "resorce_id": null,
                "text_option": {
                    "character_name": null,
                    "character_text": null,
                    "voice": null,
                    "voice_option": null
                }
            },
            {
                "command_id": 209,
                "command": "Character",
                "command_option": "Move",
                "command_time": 0.3,
                "resorce_id": 200130,
                "character_option": {
                    "body_variation": 1,
                    "face_variation": 4,
                    "position_x": 2,
                    "position_y": 0,
                    "scale": null
                }
            }
        ]
    },
    {
        "command_id": 211,
        "command": "Character",
        "command_option": "Move",
        "command_time": 0.3,
        "resorce_id": 200130,
        "character_option": {
            "body_variation": 1,
            "face_variation": 4,
            "position_x": -2,
            "position_y": 0,
            "scale": null
        }
    },
    {
        "command": "Block",
        "list": [
            {
                "command_id": 213,
                "command": "Character",
                "command_option": "Move",
                "command_time": 0.3,
                "resorce_id": 200130,
                "character_option": {
                    "body_variation": 1,
                    "face_variation": 4,
                    "position_x": 0,
                    "position_y": 0,
                    "scale": null
                }
            },
            {
                "command_id": 214,
                "command": "Text",
                "command_option": null,
                "command_time": null,
                "resorce_id": 200130,
                "text_option": {
                    "character_name": "アルナイル",
                    "character_text": "…………",
                    "voice": "200110_adv_003_004_001",
                    "voice_option": null
                }
            }
        ]
    },
    {
        "command": "Block",
        "list": [
            {
                "command_id": 217,
                "command": "Character",
                "command_option": "On",
                "command_time": null,
                "resorce_id": 200130,
                "character_option": {
                    "body_variation": 1,
                    "face_variation": 4,
                    "position_x": 0,
                    "position_y": 0,
                    "scale": null
                }
            },
            {
                "command_id": 218,
                "command": "Text",
                "command_option": null,
                "command_time": null,
                "resorce_id": 200130,
                "text_option": {
                    "character_name": "アルナイル",
                    "character_text": "キ、キスって……い、言いました……か……？",
                    "voice": "200100_adv_002_001_005",
                    "voice_option": null
                }
            }
        ]
    },
    {
        "command": "Block",
        "list": [
            {
                "command_id": 221,
                "command": "Shake",
                "command_option": 0.18,
                "command_time": 0.2,
                "resorce_id": 200130
            },
            {
                "command_id": 222,
                "command": "Character",
                "command_option": "On",
                "command_time": null,
                "resorce_id": 200130,
                "character_option": {
                    "body_variation": 1,
                    "face_variation": 9,
                    "position_x": 0,
                    "position_y": 0,
                    "scale": null
                }
            },
            {
                "command_id": 223,
                "command": "Text",
                "command_option": null,
                "command_time": null,
                "resorce_id": 200130,
                "text_option": {
                    "character_name": "アルナイル",
                    "character_text": "！！",
                    "voice": "200110_adv_003_008_001",
                    "voice_option": null
                }
            }
        ]
    },
    {
        "command": "Block",
        "list": [
            {
                "command_id": 226,
                "command": "Text",
                "command_option": "Off",
                "command_time": 0.1,
                "resorce_id": null,
                "text_option": {
                    "character_name": null,
                    "character_text": null,
                    "voice": null,
                    "voice_option": null
                }
            },
            {
                "command_id": 227,
                "command": "Character",
                "command_option": "Move",
                "command_time": 0.2,
                "resorce_id": 200130,
                "character_option": {
                    "body_variation": 1,
                    "face_variation": 9,
                    "position_x": 2,
                    "position_y": 0,
                    "scale": null
                }
            }
        ]
    },
    {
        "command_id": 229,
        "command": "Character",
        "command_option": "Move",
        "command_time": 0.2,
        "resorce_id": 200130,
        "character_option": {
            "body_variation": 1,
            "face_variation": 9,
            "position_x": -2,
            "position_y": 0,
            "scale": null
        }
    },
    {
        "command": "Block",
        "list": [
            {
                "command_id": 231,
                "command": "Character",
                "command_option": "Move",
                "command_time": 0.2,
                "resorce_id": 200130,
                "character_option": {
                    "body_variation": 1,
                    "face_variation": 9,
                    "position_x": 0,
                    "position_y": 0,
                    "scale": null
                }
            },
            {
                "command_id": 232,
                "command": "Text",
                "command_option": null,
                "command_time": null,
                "resorce_id": 200130,
                "text_option": {
                    "character_name": "アルナイル",
                    "character_text": "（はわっ！　マスターがうんって頷かれました……！\n　や、やっぱり聞き間違いじゃなかったです……！）",
                    "voice": "200120_adv_003_006_001",
                    "voice_option": null
                }
            }
        ]
    },
    {
        "command": "Block",
        "list": [
            {
                "command_id": 235,
                "command": "Text",
                "command_option": "Off",
                "command_time": 0.1,
                "resorce_id": null,
                "text_option": {
                    "character_name": null,
                    "character_text": null,
                    "voice": null,
                    "voice_option": null
                }
            },
            {
                "command_id": 236,
                "command": "Character",
                "command_option": "Move",
                "command_time": 0.1,
                "resorce_id": 200130,
                "character_option": {
                    "body_variation": 1,
                    "face_variation": 11,
                    "position_x": 2,
                    "position_y": 0,
                    "scale": null
                }
            }
        ]
    },
    {
        "command_id": 238,
        "command": "Character",
        "command_option": "Move",
        "command_time": 0.1,
        "resorce_id": 200130,
        "character_option": {
            "body_variation": 1,
            "face_variation": 11,
            "position_x": -2,
            "position_y": 0,
            "scale": null
        }
    },
    {
        "command": "Block",
        "list": [
            {
                "command_id": 240,
                "command": "Character",
                "command_option": "Move",
                "command_time": 0.1,
                "resorce_id": 200130,
                "character_option": {
                    "body_variation": 1,
                    "face_variation": 11,
                    "position_x": 0,
                    "position_y": 0,
                    "scale": null
                }
            },
            {
                "command_id": 241,
                "command": "Text",
                "command_option": null,
                "command_time": null,
                "resorce_id": 200130,
                "text_option": {
                    "character_name": "アルナイル",
                    "character_text": "あの……で、では……っ……",
                    "voice": "200110_adv_003_013_001",
                    "voice_option": null
                }
            }
        ]
    },
    {
        "command": "Block",
        "list": [
            {
                "command_id": 244,
                "command": "Text",
                "command_option": "Off",
                "command_time": 0.1,
                "resorce_id": null,
                "text_option": {
                    "character_name": null,
                    "character_text": null,
                    "voice": null,
                    "voice_option": null
                }
            },
            {
                "command_id": 245,
                "command": "Character",
                "command_option": "Move",
                "command_time": 0.30000000000000004,
                "resorce_id": 200130,
                "character_option": {
                    "body_variation": 1,
                    "face_variation": 2,
                    "position_x": 0,
                    "position_y": -5,
                    "scale": null
                }
            }
        ]
    },
    {
        "command_id": 247,
        "command": "Character",
        "command_option": "Move",
        "command_time": 0.22499999999999998,
        "resorce_id": 200130,
        "character_option": {
            "body_variation": 1,
            "face_variation": 2,
            "position_x": 0,
            "position_y": -7,
            "scale": null
        }
    },
    {
        "command_id": 248,
        "command": "Character",
        "command_option": "Move",
        "command_time": 0.22499999999999998,
        "resorce_id": 200130,
        "character_option": {
            "body_variation": 1,
            "face_variation": 2,
            "position_x": 0,
            "position_y": -3,
            "scale": null
        }
    },
    {
        "command": "Block",
        "list": [
            {
                "command_id": 250,
                "command": "Character",
                "command_option": "Move",
                "command_time": 0.07500000000000001,
                "resorce_id": 200130,
                "character_option": {
                    "body_variation": 1,
                    "face_variation": 2,
                    "position_x": 0,
                    "position_y": 0,
                    "scale": null
                }
            },
            {
                "command_id": 251,
                "command": "Text",
                "command_option": null,
                "command_time": null,
                "resorce_id": 200130,
                "text_option": {
                    "character_name": "アルナイル",
                    "character_text": "……お願い、します……",
                    "voice": "200110_adv_004_002_001",
                    "voice_option": null
                }
            }
        ]
    },
    {
        "command": "Block",
        "list": [
            {
                "command_id": 254,
                "command": "Character",
                "command_option": "OffAll",
                "command_time": 0.2,
                "resorce_id": null,
                "character_option": {
                    "body_variation": null,
                    "face_variation": null,
                    "position_x": null,
                    "position_y": null,
                    "scale": null
                }
            },
            {
                "command_id": 255,
                "command": "Text",
                "command_option": "Off",
                "command_time": 0.2,
                "resorce_id": null,
                "text_option": {
                    "character_name": null,
                    "character_text": null,
                    "voice": null,
                    "voice_option": null
                }
            }
        ]
    },
    {
        "command_id": 257,
        "command": "Wait",
        "command_option": null,
        "command_time": 0.2,
        "resorce_id": null
    },
    {
        "command": "Block",
        "list": [
            {
                "command_id": 259,
                "command": "Character",
                "command_option": "On",
                "command_time": 0.25,
                "resorce_id": 200130,
                "character_option": {
                    "body_variation": 1,
                    "face_variation": 3,
                    "position_x": 0,
                    "position_y": -40,
                    "scale": 1.0621999999999998
                }
            },
            {
                "command_id": 260,
                "command": "Character",
                "command_option": "Zoom",
                "command_time": 0.25,
                "resorce_id": 200130,
                "character_option": {
                    "body_variation": null,
                    "face_variation": null,
                    "position_x": null,
                    "position_y": null,
                    "scale": 1.081
                }
            }
        ]
    },
    {
        "command_id": 262,
        "command": "Wait",
        "command_option": null,
        "command_time": 0.3,
        "resorce_id": null
    },
    {
        "command": "Block",
        "list": [
            {
                "command_id": 265,
                "command": "Character",
                "command_option": "On",
                "command_time": null,
                "resorce_id": 200130,
                "character_option": {
                    "body_variation": 1,
                    "face_variation": 3,
                    "position_x": 0,
                    "position_y": -40,
                    "scale": null
                }
            },
            {
                "command_id": 266,
                "command": "Text",
                "command_option": null,
                "command_time": null,
                "resorce_id": 200130,
                "text_option": {
                    "character_name": "アルナイル",
                    "character_text": "…………",
                    "voice": "200120_adv_003_010_001",
                    "voice_option": null
                }
            }
        ]
    },
    {
        "command": "Block",
        "list": [
            {
                "command_id": 270,
                "command": "Text",
                "command_option": "Off",
                "command_time": 0.15,
                "resorce_id": null,
                "text_option": {
                    "character_name": null,
                    "character_text": null,
                    "voice": null,
                    "voice_option": null
                }
            },
            {
                "command_id": 271,
                "command": "Character",
                "command_option": "Move",
                "command_time": 0.15,
                "resorce_id": 200130,
                "character_option": {
                    "body_variation": 1,
                    "face_variation": 12,
                    "position_x": 0,
                    "position_y": -43,
                    "scale": null
                }
            },
            {
                "command_id": 272,
                "command": "Character",
                "command_option": "Zoom",
                "command_time": 0.15,
                "resorce_id": 200130,
                "character_option": {
                    "body_variation": null,
                    "face_variation": null,
                    "position_x": null,
                    "position_y": null,
                    "scale": 1.08476
                }
            }
        ]
    },
    {
        "command": "Block",
        "list": [
            {
                "command_id": 275,
                "command": "Character",
                "command_option": "Zoom",
                "command_time": 0.15,
                "resorce_id": 200130,
                "character_option": {
                    "body_variation": null,
                    "face_variation": null,
                    "position_x": null,
                    "position_y": null,
                    "scale": 1.081
                }
            },
            {
                "command_id": 276,
                "command": "Character",
                "command_option": "Move",
                "command_time": 0.15,
                "resorce_id": 200130,
                "character_option": {
                    "body_variation": 1,
                    "face_variation": 12,
                    "position_x": 0,
                    "position_y": -40,
                    "scale": null
                }
            },
            {
                "command_id": 277,
                "command": "Text",
                "command_option": null,
                "command_time": null,
                "resorce_id": 200130,
                "text_option": {
                    "character_name": "アルナイル",
                    "character_text": "（チュ）",
                    "voice": "200100_adv_003_021_001",
                    "voice_option": null
                }
            }
        ]
    },
    {
        "command_id": 281,
        "command": "Transition",
        "command_option": "Out",
        "command_time": 0.5,
        "resorce_id": null
    },
    {
        "command": "Block",
        "list": [
            {
                "command_id": 283,
                "command": "Character",
                "command_option": "OffAll",
                "command_time": 0.1,
                "resorce_id": null,
                "character_option": {
                    "body_variation": null,
                    "face_variation": null,
                    "position_x": null,
                    "position_y": null,
                    "scale": null
                }
            },
            {
                "command_id": 284,
                "command": "Text",
                "command_option": "Off",
                "command_time": 0.1,
                "resorce_id": null,
                "text_option": {
                    "character_name": null,
                    "character_text": null,
                    "voice": null,
                    "voice_option": null
                }
            }
        ]
    },
    {
        "command_id": 286,
        "command": "Wait",
        "command_option": null,
        "command_time": 1,
        "resorce_id": null
    },
    {
        "command_id": 287,
        "command": "Transition",
        "command_option": "In",
        "command_time": 0.5,
        "resorce_id": null
    },
    {
        "command_id": 288,
        "command": "Wait",
        "command_option": null,
        "command_time": 0.6,
        "resorce_id": null
    },
    {
        "command": "Block",
        "list": [
            {
                "command_id": 290,
                "command": "Character",
                "command_option": "On",
                "command_time": 0.15,
                "resorce_id": 200130,
                "character_option": {
                    "body_variation": 1,
                    "face_variation": 6,
                    "position_x": 0,
                    "position_y": 0,
                    "scale": 0.94
                }
            },
            {
                "command_id": 291,
                "command": "Character",
                "command_option": "Move",
                "command_time": 0.15,
                "resorce_id": 200130,
                "character_option": {
                    "body_variation": 1,
                    "face_variation": 6,
                    "position_x": 0,
                    "position_y": -5,
                    "scale": null
                }
            }
        ]
    },
    {
        "command_id": 293,
        "command": "Character",
        "command_option": "Move",
        "command_time": 0.1,
        "resorce_id": 200130,
        "character_option": {
            "body_variation": 1,
            "face_variation": 6,
            "position_x": 0,
            "position_y": -7,
            "scale": null
        }
    },
    {
        "command_id": 294,
        "command": "Character",
        "command_option": "Move",
        "command_time": 0.1,
        "resorce_id": 200130,
        "character_option": {
            "body_variation": 1,
            "face_variation": 6,
            "position_x": 0,
            "position_y": -3,
            "scale": null
        }
    },
    {
        "command": "Block",
        "list": [
            {
                "command_id": 296,
                "command": "Character",
                "command_option": "Move",
                "command_time": 0.02,
                "resorce_id": 200130,
                "character_option": {
                    "body_variation": 1,
                    "face_variation": 6,
                    "position_x": 0,
                    "position_y": 0,
                    "scale": null
                }
            },
            {
                "command_id": 297,
                "command": "Text",
                "command_option": null,
                "command_time": null,
                "resorce_id": 200130,
                "text_option": {
                    "character_name": "アルナイル",
                    "character_text": "やっぱりこの衣装すごいですマスター！",
                    "voice": "200100_adv_003_018_001",
                    "voice_option": null
                }
            }
        ]
    },
    {
        "command": "Block",
        "list": [
            {
                "command_id": 300,
                "command": "Character",
                "command_option": "On",
                "command_time": null,
                "resorce_id": 200130,
                "character_option": {
                    "body_variation": 1,
                    "face_variation": 12,
                    "position_x": 0,
                    "position_y": 0,
                    "scale": null
                }
            },
            {
                "command_id": 301,
                "command": "Text",
                "command_option": null,
                "command_time": null,
                "resorce_id": 200130,
                "text_option": {
                    "character_name": "アルナイル",
                    "character_text": "マスターとキス……してから、パワーが全然ちがいますっ",
                    "voice": "200100_adv_000_001_039",
                    "voice_option": null
                }
            }
        ]
    },
    {
        "command": "Block",
        "list": [
            {
                "command_id": 304,
                "command": "Text",
                "command_option": "Off",
                "command_time": 0.1,
                "resorce_id": null,
                "text_option": {
                    "character_name": null,
                    "character_text": null,
                    "voice": null,
                    "voice_option": null
                }
            },
            {
                "command_id": 305,
                "command": "Character",
                "command_option": "Move",
                "command_time": 0.2,
                "resorce_id": 200130,
                "character_option": {
                    "body_variation": 1,
                    "face_variation": 3,
                    "position_x": 0,
                    "position_y": -5,
                    "scale": null
                }
            }
        ]
    },
    {
        "command_id": 307,
        "command": "Character",
        "command_option": "Move",
        "command_time": 0.15,
        "resorce_id": 200130,
        "character_option": {
            "body_variation": 1,
            "face_variation": 3,
            "position_x": 0,
            "position_y": -7,
            "scale": null
        }
    },
    {
        "command_id": 308,
        "command": "Character",
        "command_option": "Move",
        "command_time": 0.15,
        "resorce_id": 200130,
        "character_option": {
            "body_variation": 1,
            "face_variation": 3,
            "position_x": 0,
            "position_y": -3,
            "scale": null
        }
    },
    {
        "command": "Block",
        "list": [
            {
                "command_id": 310,
                "command": "Character",
                "command_option": "Move",
                "command_time": 0.05,
                "resorce_id": 200130,
                "character_option": {
                    "body_variation": 1,
                    "face_variation": 3,
                    "position_x": 0,
                    "position_y": 0,
                    "scale": null
                }
            },
            {
                "command_id": 311,
                "command": "Text",
                "command_option": null,
                "command_time": null,
                "resorce_id": 200130,
                "text_option": {
                    "character_name": "アルナイル",
                    "character_text": "はあ……。ちゃんとわかってたハズなんですけど……",
                    "voice": "200100_adv_003_010_001",
                    "voice_option": null
                }
            }
        ]
    },
    {
        "command": "Block",
        "list": [
            {
                "command_id": 315,
                "command": "Text",
                "command_option": "Off",
                "command_time": 0.1,
                "resorce_id": null,
                "text_option": {
                    "character_name": null,
                    "character_text": null,
                    "voice": null,
                    "voice_option": null
                }
            },
            {
                "command_id": 316,
                "command": "Character",
                "command_option": "Move",
                "command_time": 0.2,
                "resorce_id": 200130,
                "character_option": {
                    "body_variation": 1,
                    "face_variation": 4,
                    "position_x": 2,
                    "position_y": 0,
                    "scale": null
                }
            }
        ]
    },
    {
        "command_id": 318,
        "command": "Character",
        "command_option": "Move",
        "command_time": 0.2,
        "resorce_id": 200130,
        "character_option": {
            "body_variation": 1,
            "face_variation": 4,
            "position_x": -2,
            "position_y": 0,
            "scale": null
        }
    },
    {
        "command": "Block",
        "list": [
            {
                "command_id": 320,
                "command": "Character",
                "command_option": "Move",
                "command_time": 0.2,
                "resorce_id": 200130,
                "character_option": {
                    "body_variation": 1,
                    "face_variation": 4,
                    "position_x": 0,
                    "position_y": 0,
                    "scale": null
                }
            },
            {
                "command_id": 321,
                "command": "Text",
                "command_option": null,
                "command_time": null,
                "resorce_id": 200130,
                "text_option": {
                    "character_name": "アルナイル",
                    "character_text": "やっぱり……ジブリールって、\nアモーレの力で戦う天使なんですね……",
                    "voice": "200120_adv_001_002_001",
                    "voice_option": null
                }
            }
        ]
    },
    {
        "command": "Block",
        "list": [
            {
                "command_id": 324,
                "command": "Text",
                "command_option": "Off",
                "command_time": 0.1,
                "resorce_id": null,
                "text_option": {
                    "character_name": null,
                    "character_text": null,
                    "voice": null,
                    "voice_option": null
                }
            },
            {
                "command_id": 325,
                "command": "Character",
                "command_option": "Move",
                "command_time": 0.2,
                "resorce_id": 200130,
                "character_option": {
                    "body_variation": 1,
                    "face_variation": 3,
                    "position_x": 0,
                    "position_y": -5,
                    "scale": null
                }
            }
        ]
    },
    {
        "command_id": 327,
        "command": "Character",
        "command_option": "Move",
        "command_time": 0.15,
        "resorce_id": 200130,
        "character_option": {
            "body_variation": 1,
            "face_variation": 3,
            "position_x": 0,
            "position_y": -7,
            "scale": null
        }
    },
    {
        "command_id": 328,
        "command": "Character",
        "command_option": "Move",
        "command_time": 0.15,
        "resorce_id": 200130,
        "character_option": {
            "body_variation": 1,
            "face_variation": 3,
            "position_x": 0,
            "position_y": -3,
            "scale": null
        }
    },
    {
        "command_id": 329,
        "command": "Character",
        "command_option": "Move",
        "command_time": 0.05,
        "resorce_id": 200130,
        "character_option": {
            "body_variation": 1,
            "face_variation": 3,
            "position_x": 0,
            "position_y": 0,
            "scale": null
        }
    },
    {
        "command_id": 330,
        "command": "Wait",
        "command_option": null,
        "command_time": 0.25,
        "resorce_id": null
    },
    {
        "command_id": 331,
        "command": "Character",
        "command_option": "Move",
        "command_time": 0.2,
        "resorce_id": 200130,
        "character_option": {
            "body_variation": 1,
            "face_variation": 6,
            "position_x": 2,
            "position_y": 0,
            "scale": null
        }
    },
    {
        "command_id": 332,
        "command": "Character",
        "command_option": "Move",
        "command_time": 0.2,
        "resorce_id": 200130,
        "character_option": {
            "body_variation": 1,
            "face_variation": 6,
            "position_x": -2,
            "position_y": 0,
            "scale": null
        }
    },
    {
        "command": "Block",
        "list": [
            {
                "command_id": 334,
                "command": "Character",
                "command_option": "Move",
                "command_time": 0.2,
                "resorce_id": 200130,
                "character_option": {
                    "body_variation": 1,
                    "face_variation": 6,
                    "position_x": 0,
                    "position_y": 0,
                    "scale": null
                }
            },
            {
                "command_id": 335,
                "command": "Text",
                "command_option": null,
                "command_time": null,
                "resorce_id": 200130,
                "text_option": {
                    "character_name": "アルナイル",
                    "character_text": "なんか、再確認しちゃいましたねマスター、エヘヘ……",
                    "voice": "200120_adv_003_004_001",
                    "voice_option": null
                }
            }
        ]
    },
    {
        "command": "Block",
        "list": [
            {
                "command_id": 338,
                "command": "Character",
                "command_option": "On",
                "command_time": null,
                "resorce_id": 200130,
                "character_option": {
                    "body_variation": 1,
                    "face_variation": 9,
                    "position_x": 0,
                    "position_y": 0,
                    "scale": null
                }
            },
            {
                "command_id": 339,
                "command": "Text",
                "command_option": null,
                "command_time": null,
                "resorce_id": 200130,
                "text_option": {
                    "character_name": "アルナイル",
                    "character_text": "戦闘のためじゃなくてもキスはいつでもしたい、ですか？",
                    "voice": "200120_adv_002_001_001",
                    "voice_option": null
                }
            }
        ]
    },
    {
        "command": "Block",
        "list": [
            {
                "command_id": 343,
                "command": "Text",
                "command_option": "Off",
                "command_time": 0.1,
                "resorce_id": null,
                "text_option": {
                    "character_name": null,
                    "character_text": null,
                    "voice": null,
                    "voice_option": null
                }
            },
            {
                "command_id": 344,
                "command": "Character",
                "command_option": "Move",
                "command_time": 0.15,
                "resorce_id": 200130,
                "character_option": {
                    "body_variation": 1,
                    "face_variation": 5,
                    "position_x": 2,
                    "position_y": 0,
                    "scale": null
                }
            }
        ]
    },
    {
        "command_id": 346,
        "command": "Character",
        "command_option": "Move",
        "command_time": 0.15,
        "resorce_id": 200130,
        "character_option": {
            "body_variation": 1,
            "face_variation": 5,
            "position_x": -2,
            "position_y": 0,
            "scale": null
        }
    },
    {
        "command_id": 347,
        "command": "Character",
        "command_option": "Move",
        "command_time": 0.15,
        "resorce_id": 200130,
        "character_option": {
            "body_variation": 1,
            "face_variation": 4,
            "position_x": 2,
            "position_y": 0,
            "scale": null
        }
    },
    {
        "command_id": 348,
        "command": "Character",
        "command_option": "Move",
        "command_time": 0.15,
        "resorce_id": 200130,
        "character_option": {
            "body_variation": 1,
            "face_variation": 4,
            "position_x": -2,
            "position_y": 0,
            "scale": null
        }
    },
    {
        "command": "Block",
        "list": [
            {
                "command_id": 350,
                "command": "Character",
                "command_option": "Move",
                "command_time": 0.15,
                "resorce_id": 200130,
                "character_option": {
                    "body_variation": 1,
                    "face_variation": 4,
                    "position_x": 0,
                    "position_y": 0,
                    "scale": null
                }
            },
            {
                "command_id": 351,
                "command": "Text",
                "command_option": null,
                "command_time": null,
                "resorce_id": 200130,
                "text_option": {
                    "character_name": "アルナイル",
                    "character_text": "ひゃあ……",
                    "voice": "200100_adv_000_001_046",
                    "voice_option": null
                }
            }
        ]
    },
    {
        "command": "Block",
        "list": [
            {
                "command_id": 354,
                "command": "Text",
                "command_option": "Off",
                "command_time": 0.1,
                "resorce_id": null,
                "text_option": {
                    "character_name": null,
                    "character_text": null,
                    "voice": null,
                    "voice_option": null
                }
            },
            {
                "command_id": 355,
                "command": "Character",
                "command_option": "Move",
                "command_time": 0.2,
                "resorce_id": 200130,
                "character_option": {
                    "body_variation": 1,
                    "face_variation": 4,
                    "position_x": 0,
                    "position_y": -5,
                    "scale": null
                }
            }
        ]
    },
    {
        "command_id": 357,
        "command": "Character",
        "command_option": "Move",
        "command_time": 0.15,
        "resorce_id": 200130,
        "character_option": {
            "body_variation": 1,
            "face_variation": 4,
            "position_x": 0,
            "position_y": -7,
            "scale": null
        }
    },
    {
        "command_id": 358,
        "command": "Character",
        "command_option": "Move",
        "command_time": 0.15,
        "resorce_id": 200130,
        "character_option": {
            "body_variation": 1,
            "face_variation": 4,
            "position_x": 0,
            "position_y": -3,
            "scale": null
        }
    },
    {
        "command": "Block",
        "list": [
            {
                "command_id": 360,
                "command": "Character",
                "command_option": "Move",
                "command_time": 0.05,
                "resorce_id": 200130,
                "character_option": {
                    "body_variation": 1,
                    "face_variation": 4,
                    "position_x": 0,
                    "position_y": 0,
                    "scale": null
                }
            },
            {
                "command_id": 361,
                "command": "Text",
                "command_option": null,
                "command_time": null,
                "resorce_id": 200130,
                "text_option": {
                    "character_name": "アルナイル",
                    "character_text": "わたしもです、マスター……",
                    "voice": "200100_adv_000_001_035",
                    "voice_option": null
                }
            }
        ]
    },
    {
        "command": "Block",
        "list": [
            {
                "command_id": 364,
                "command": "Character",
                "command_option": "OffAll",
                "command_time": 0.2,
                "resorce_id": null,
                "character_option": {
                    "body_variation": null,
                    "face_variation": null,
                    "position_x": null,
                    "position_y": null,
                    "scale": null
                }
            },
            {
                "command_id": 365,
                "command": "Text",
                "command_option": "Off",
                "command_time": 0.2,
                "resorce_id": null,
                "text_option": {
                    "character_name": null,
                    "character_text": null,
                    "voice": null,
                    "voice_option": null
                }
            }
        ]
    },
    {
        "command_id": 367,
        "command": "Wait",
        "command_option": null,
        "command_time": 0.2,
        "resorce_id": null
    },
    {
        "command": "Block",
        "list": [
            {
                "command_id": 369,
                "command": "Character",
                "command_option": "On",
                "command_time": 0.2,
                "resorce_id": 200130,
                "character_option": {
                    "body_variation": 1,
                    "face_variation": 3,
                    "position_x": 0,
                    "position_y": -40,
                    "scale": 1.0621999999999998
                }
            },
            {
                "command_id": 370,
                "command": "Character",
                "command_option": "Zoom",
                "command_time": 0.2,
                "resorce_id": 200130,
                "character_option": {
                    "body_variation": null,
                    "face_variation": null,
                    "position_x": null,
                    "position_y": null,
                    "scale": 1.081
                }
            }
        ]
    },
    {
        "command_id": 372,
        "command": "Wait",
        "command_option": null,
        "command_time": 0.2,
        "resorce_id": null
    },
    {
        "command": "Block",
        "list": [
            {
                "command_id": 375,
                "command": "Character",
                "command_option": "On",
                "command_time": null,
                "resorce_id": 200130,
                "character_option": {
                    "body_variation": 1,
                    "face_variation": 3,
                    "position_x": 0,
                    "position_y": -40,
                    "scale": null
                }
            },
            {
                "command_id": 376,
                "command": "Text",
                "command_option": null,
                "command_time": null,
                "resorce_id": 200130,
                "text_option": {
                    "character_name": "アルナイル",
                    "character_text": "…………",
                    "voice": "200120_adv_003_010_001",
                    "voice_option": null
                }
            }
        ]
    },
    {
        "command": "Block",
        "list": [
            {
                "command_id": 380,
                "command": "Text",
                "command_option": "Off",
                "command_time": 0.175,
                "resorce_id": null,
                "text_option": {
                    "character_name": null,
                    "character_text": null,
                    "voice": null,
                    "voice_option": null
                }
            },
            {
                "command_id": 381,
                "command": "Character",
                "command_option": "Move",
                "command_time": 0.175,
                "resorce_id": 200130,
                "character_option": {
                    "body_variation": 1,
                    "face_variation": 12,
                    "position_x": 0,
                    "position_y": -43,
                    "scale": null
                }
            },
            {
                "command_id": 382,
                "command": "Character",
                "command_option": "Zoom",
                "command_time": 0.175,
                "resorce_id": 200130,
                "character_option": {
                    "body_variation": null,
                    "face_variation": null,
                    "position_x": null,
                    "position_y": null,
                    "scale": 1.08476
                }
            }
        ]
    },
    {
        "command": "Block",
        "list": [
            {
                "command_id": 385,
                "command": "Character",
                "command_option": "Zoom",
                "command_time": 0.175,
                "resorce_id": 200130,
                "character_option": {
                    "body_variation": null,
                    "face_variation": null,
                    "position_x": null,
                    "position_y": null,
                    "scale": 1.081
                }
            },
            {
                "command_id": 386,
                "command": "Character",
                "command_option": "Move",
                "command_time": 0.175,
                "resorce_id": 200130,
                "character_option": {
                    "body_variation": 1,
                    "face_variation": 12,
                    "position_x": 0,
                    "position_y": -40,
                    "scale": null
                }
            },
            {
                "command_id": 387,
                "command": "Text",
                "command_option": null,
                "command_time": null,
                "resorce_id": 200130,
                "text_option": {
                    "character_name": "アルナイル",
                    "character_text": "（チュ）",
                    "voice": "200100_adv_003_021_001",
                    "voice_option": null
                }
            }
        ]
    },
    {
        "command_id": 390,
        "command": "Transition",
        "command_option": "Out",
        "command_time": 0.5,
        "resorce_id": null
    },
    {
        "command": "Block",
        "list": [
            {
                "command_id": 392,
                "command": "Bg",
                "command_option": "On",
                "command_time": 0.1,
                "resorce_id": 1,
                "bg_option": {
                    "position_x": null,
                    "position_y": null,
                    "scale": null
                }
            },
            {
                "command_id": 393,
                "command": "Character",
                "command_option": "OffAll",
                "command_time": 0.1,
                "resorce_id": null,
                "character_option": {
                    "body_variation": null,
                    "face_variation": null,
                    "position_x": null,
                    "position_y": null,
                    "scale": null
                }
            },
            {
                "command_id": 394,
                "command": "Text",
                "command_option": "Off",
                "command_time": 0.1,
                "resorce_id": null,
                "text_option": {
                    "character_name": null,
                    "character_text": null,
                    "voice": null,
                    "voice_option": null
                }
            }
        ]
    },
    {
        "command_id": 396,
        "command": "Wait",
        "command_option": null,
        "command_time": 0.3,
        "resorce_id": null
    },
    {
        "command_id": 397,
        "command": "Transition",
        "command_option": "In",
        "command_time": 0.2,
        "resorce_id": null
    },
    {
        "command_id": 398,
        "command": "Wait",
        "command_option": null,
        "command_time": 0.3,
        "resorce_id": null
    },
    {
        "command_id": 399,
        "command": "Text",
        "command_option": null,
        "command_time": null,
        "resorce_id": 200130,
        "text_option": {
            "character_name": "アルナイル",
            "character_text": "……エヘヘ……",
            "voice": "200100_adv_003_004_001",
            "voice_option": null
        }
    },
    {
        "command_id": 400,
        "command": "Text",
        "command_option": null,
        "command_time": null,
        "resorce_id": 200130,
        "text_option": {
            "character_name": "アルナイル",
            "character_text": "マスター、大好きですよ……♪",
            "voice": "200100_adv_001_002_002",
            "voice_option": null
        }
    },
    {
        "command": "Block",
        "list": [
            {
                "command_id": 402,
                "command": "Bgm",
                "command_option": "Off",
                "command_time": 2,
                "resorce_id": 100101
            },
            {
                "command_id": 403,
                "command": "Transition",
                "command_option": "Out",
                "command_time": 2,
                "resorce_id": 0
            }
        ]
    },
    {
        "command_id": 405,
        "command": "End",
        "command_option": null,
        "command_time": null,
        "resorce_id": null
    }
]