[
    {
        "command": "Block",
        "list": [
            {
                "command_id": 2,
                "command": "Bg",
                "command_option": "On",
                "command_time": 0,
                "resorce_id": 100149
            },
            {
                "command_id": 3,
                "command": "Transition",
                "command_option": "In",
                "command_time": 2,
                "resorce_id": 0
            }
        ]
    },
    {
        "command_id": 5,
        "command": "Title",
        "command_option": null,
        "command_time": null,
        "resorce_id": null,
        "title_option": {
            "main_text": "魅惑のバスト",
            "sub_text": "ザムザギエル"
        }
    },
    {
        "command_id": 6,
        "command": "Character",
        "command_option": "On",
        "command_time": 0.5,
        "resorce_id": 102200,
        "character_option": {
            "body_variation": 1,
            "face_variation": 9,
            "position_x": 0,
            "position_y": 0,
            "scale": null
        }
    },
    {
        "command_id": 7,
        "command": "Wait",
        "command_option": null,
        "command_time": 0.1,
        "resorce_id": null
    },
    {
        "command_id": 8,
        "command": "Bgm",
        "command_option": "On",
        "command_time": 0,
        "resorce_id": 100101
    },
    {
        "command_id": 10,
        "command": "Text",
        "command_option": null,
        "command_time": null,
        "resorce_id": 102200,
        "text_option": {
            "character_name": "ザムザギエル",
            "character_text": "……なあに？　マスター君ったら、\nそんなに先生のおっぱいばっかり見つめて……",
            "voice": "102200_adv_002_003_001",
            "voice_option": null
        }
    },
    {
        "command": "Block",
        "list": [
            {
                "command_id": 12,
                "command": "Character",
                "command_option": "On",
                "command_time": null,
                "resorce_id": 102200,
                "character_option": {
                    "body_variation": 1,
                    "face_variation": 5,
                    "position_x": 0,
                    "position_y": 0,
                    "scale": null
                }
            },
            {
                "command_id": 13,
                "command": "Text",
                "command_option": null,
                "command_time": null,
                "resorce_id": 102200,
                "text_option": {
                    "character_name": "ザムザギエル",
                    "character_text": "興味があるのはおっぱいだけなのかしら？　マスター君は、\nおっぱいが大きかったら、先生じゃなくても誰でも良いのかしら？",
                    "voice": "102200_adv_001_005_001",
                    "voice_option": null
                }
            }
        ]
    },
    {
        "command": "Block",
        "list": [
            {
                "command_id": 16,
                "command": "Character",
                "command_option": "On",
                "command_time": null,
                "resorce_id": 102200,
                "character_option": {
                    "body_variation": 1,
                    "face_variation": 8,
                    "position_x": 0,
                    "position_y": 0,
                    "scale": null
                }
            },
            {
                "command_id": 17,
                "command": "Text",
                "command_option": null,
                "command_time": null,
                "resorce_id": 102200,
                "text_option": {
                    "character_name": "ザムザギエル",
                    "character_text": "先生は君のこと、けっこう気に入ってるのだけど……残念ね。\nあらあら、そんなに慌てて、だいじょうぶ、冗談よ。ふふ",
                    "voice": "102200_adv_003_003_001",
                    "voice_option": null
                }
            }
        ]
    },
    {
        "command": "Block",
        "list": [
            {
                "command_id": 20,
                "command": "Character",
                "command_option": "On",
                "command_time": null,
                "resorce_id": 102200,
                "character_option": {
                    "body_variation": 1,
                    "face_variation": 1,
                    "position_x": 0,
                    "position_y": 0,
                    "scale": null
                }
            },
            {
                "command_id": 21,
                "command": "Text",
                "command_option": null,
                "command_time": null,
                "resorce_id": 102200,
                "text_option": {
                    "character_name": "ザムザギエル",
                    "character_text": "マスター君、先生のおっぱいのサイズが気になる？　いいわよ、\nこの天使の属性を覚えたら、実際に触ってはからせてあ、げ、る",
                    "voice": "102200_battle_000_start_001",
                    "voice_option": null
                }
            }
        ]
    },
    {
        "command": "Block",
        "list": [
            {
                "command_id": 24,
                "command": "Character",
                "command_option": "On",
                "command_time": null,
                "resorce_id": 102200,
                "character_option": {
                    "body_variation": 1,
                    "face_variation": 6,
                    "position_x": 0,
                    "position_y": 0,
                    "scale": null
                }
            },
            {
                "command_id": 25,
                "command": "Text",
                "command_option": null,
                "command_time": null,
                "resorce_id": 102200,
                "text_option": {
                    "character_name": "ザムザギエル",
                    "character_text": "なあに？　そんなに驚いて……びっくりした？　うふふ。\nでもこれは冗談じゃなくて、本当に触って良いわよ？",
                    "voice": "102200_adv_003_001_001",
                    "voice_option": null
                }
            }
        ]
    },
    {
        "command": "Block",
        "list": [
            {
                "command_id": 28,
                "command": "Character",
                "command_option": "On",
                "command_time": null,
                "resorce_id": 102200,
                "character_option": {
                    "body_variation": 1,
                    "face_variation": 1,
                    "position_x": 0,
                    "position_y": 0,
                    "scale": null
                }
            },
            {
                "command_id": 29,
                "command": "Text",
                "command_option": null,
                "command_time": null,
                "resorce_id": 102200,
                "text_option": {
                    "character_name": "ザムザギエル",
                    "character_text": "えっちなことでも、そうじゃないことでも、\n興味があるのは大切なことだわ",
                    "voice": "102200_battle_000_end2_001",
                    "voice_option": null
                }
            }
        ]
    },
    {
        "command": "Block",
        "list": [
            {
                "command_id": 32,
                "command": "Character",
                "command_option": "On",
                "command_time": null,
                "resorce_id": 102200,
                "character_option": {
                    "body_variation": 1,
                    "face_variation": 6,
                    "position_x": 0,
                    "position_y": 0,
                    "scale": null
                }
            },
            {
                "command_id": 33,
                "command": "Text",
                "command_option": null,
                "command_time": null,
                "resorce_id": 102200,
                "text_option": {
                    "character_name": "ザムザギエル",
                    "character_text": "それに、君が先生のおっぱいでやる気を出して\nお勉強がはかどるのなら、先生も嬉しいわ。うふふ",
                    "voice": "102200_adv_003_010_001",
                    "voice_option": null
                }
            }
        ]
    },
    {
        "command": "Block",
        "list": [
            {
                "command_id": 36,
                "command": "Bgm",
                "command_option": "Off",
                "command_time": 2,
                "resorce_id": 100101
            },
            {
                "command_id": 37,
                "command": "Transition",
                "command_option": "Out",
                "command_time": 2,
                "resorce_id": 0
            }
        ]
    },
    {
        "command_id": 39,
        "command": "End",
        "command_option": null,
        "command_time": null,
        "resorce_id": null
    }
]